odoo/addons/attachment_zipped_download/README.rst
odoo/addons/attachment_zipped_download/__init__.py
odoo/addons/attachment_zipped_download/__manifest__.py
odoo/addons/attachment_zipped_download/controllers/__init__.py
odoo/addons/attachment_zipped_download/controllers/main.py
odoo/addons/attachment_zipped_download/i18n/attachment_zipped_download.pot
odoo/addons/attachment_zipped_download/i18n/es.po
odoo/addons/attachment_zipped_download/i18n/fr.po
odoo/addons/attachment_zipped_download/i18n/it.po
odoo/addons/attachment_zipped_download/models/__init__.py
odoo/addons/attachment_zipped_download/models/ir_attachment.py
odoo/addons/attachment_zipped_download/models/ir_attachment_action_download.py
odoo/addons/attachment_zipped_download/readme/CONTRIBUTORS.rst
odoo/addons/attachment_zipped_download/readme/DESCRIPTION.rst
odoo/addons/attachment_zipped_download/readme/USAGE.rst
odoo/addons/attachment_zipped_download/static/description/icon.png
odoo/addons/attachment_zipped_download/static/description/index.html
odoo/addons/attachment_zipped_download/tests/__init__.py
odoo/addons/attachment_zipped_download/tests/test_attachment_zipped_download.py
odoo/addons/attachment_zipped_download/tests/test_ir_attachment_action_download.py
odoo/addons/attachment_zipped_download/tests/models/__init__.py
odoo/addons/attachment_zipped_download/tests/models/res_partner.py
odoo/addons/attachment_zipped_download/views/ir_attachment_view.xml
odoo14_addon_attachment_zipped_download-14.0.2.0.0.dist-info/METADATA
odoo14_addon_attachment_zipped_download-14.0.2.0.0.dist-info/WHEEL
odoo14_addon_attachment_zipped_download-14.0.2.0.0.dist-info/top_level.txt
odoo14_addon_attachment_zipped_download-14.0.2.0.0.dist-info/RECORD
